db_app/__init__.py
db_app/connection.py
db_app/mariadb_automatization.py
db_app/postgres_automatization.py
db_app-0.0.2.dist-info/METADATA
db_app-0.0.2.dist-info/WHEEL
db_app-0.0.2.dist-info/top_level.txt
db_app-0.0.2.dist-info/RECORD
